[{"__type__":"cc.SpriteFrame","content":{"name":"button_huang_small","texture":"30OC+qxhtKgJGrn8Ay3Rav","rect":[0,0,191,76],"offset":[-0.5,0],"originalSize":[192,76],"capInsets":[0,0,0,0]}},{"__type__":"cc.SpriteFrame","content":{"name":"close_btn","texture":"334M8gYypH+7+H6LyZ01Ql","rect":[0,0,65,65],"offset":[-0.5,0.5],"originalSize":[66,66],"capInsets":[0,0,0,0]}},[{"__type__":"cc.Prefab","_name":"bindinvitor","data":{"__id__":1}},{"__type__":"cc.Node","_name":"bindinvitor","_children":[{"__id__":2},{"__id__":3},{"__id__":5},{"__id__":6},{"__id__":8},{"__id__":9}],"_components":[{"__type__":"3bbb77e935H1rt6GUt/umuQ","node":{"__id__":1}}],"_prefab":{"__type__":"cc.PrefabInfo","root":{"__id__":1},"asset":{"__uuid__":"f696oT4xtEM7j2K2VK1doP"},"fileId":"985caDgXl5H3KdiBU6YGQdw"},"_contentSize":{"__type__":"cc.Size","width":1280,"height":720},"_scale":{"__type__":"cc.Vec3","x":1,"y":1,"z":1}},{"__type__":"cc.Node","_name":"New Layout","_parent":{"__id__":1},"_components":[{"__type__":"cc.Sprite","node":{"__id__":2},"_spriteFrame":{"__uuid__":"9bvaMerUlDyary99mJa6xp"},"_type":1,"_sizeMode":0},{"__type__":"cc.Button","node":{"__id__":2},"_N$target":{"__id__":2}}],"_prefab":{"__type__":"cc.PrefabInfo","root":{"__id__":1},"asset":{"__uuid__":"f696oT4xtEM7j2K2VK1doP"},"fileId":"4e836Xd79NLgJz6WvRUxp4a"},"_opacity":200,"_color":{"__type__":"cc.Color"},"_contentSize":{"__type__":"cc.Size","width":1280,"height":720},"_scale":{"__type__":"cc.Vec3","x":1,"y":1,"z":1}},{"__type__":"cc.Node","_name":"Num25","_parent":{"__id__":1},"_children":[{"__id__":4}],"_components":[{"__type__":"cc.Sprite","node":{"__id__":3}}],"_prefab":{"__type__":"cc.PrefabInfo","root":{"__id__":1},"asset":{"__uuid__":"f696oT4xtEM7j2K2VK1doP"},"fileId":"f4450jSTCtLzZhMHLdSEbyU"},"_contentSize":{"__type__":"cc.Size","width":681,"height":477},"_scale":{"__type__":"cc.Vec3","x":1,"y":1,"z":1}},{"__type__":"cc.Node","_name":"titletext","_parent":{"__id__":3},"_components":[{"__type__":"cc.Sprite","node":{"__id__":4}}],"_prefab":{"__type__":"cc.PrefabInfo","root":{"__id__":1},"asset":{"__uuid__":"f696oT4xtEM7j2K2VK1doP"},"fileId":"7529eKB4gVGAr6btq/XdpFK"},"_contentSize":{"__type__":"cc.Size","width":199,"height":51},"_position":{"__type__":"cc.Vec3","y":206},"_scale":{"__type__":"cc.Vec3","x":1,"y":1,"z":1}},{"__type__":"cc.Node","_name":"btn_close","_parent":{"__id__":1},"_components":[{"__type__":"cc.Sprite","node":{"__id__":5},"_spriteFrame":{"__uuid__":"97Rv27429B1ICUuFw493wU"}},{"__type__":"cc.Button","node":{"__id__":5},"zoomScale":0.95,"_N$transition":3,"transition":3,"_N$normalColor":{"__type__":"cc.Color","r":255,"g":255,"b":255},"_N$target":{"__id__":5}}],"_prefab":{"__type__":"cc.PrefabInfo","root":{"__id__":1},"asset":{"__uuid__":"f696oT4xtEM7j2K2VK1doP"},"fileId":"94e55ubzQVCk5KS+2FFul8Z"},"_contentSize":{"__type__":"cc.Size","width":65,"height":65},"_position":{"__type__":"cc.Vec3","x":300,"y":204},"_scale":{"__type__":"cc.Vec3","x":1,"y":1,"z":1}},{"__type__":"cc.Node","_name":"bindbtn","_parent":{"__id__":1},"_children":[{"__id__":7}],"_components":[{"__type__":"cc.Sprite","node":{"__id__":6},"_spriteFrame":{"__uuid__":"1en6JDOIpAZ6KUtp0eXZ6P"}},{"__type__":"cc.Button","node":{"__id__":6},"zoomScale":0.95,"_N$transition":3,"transition":3,"_N$target":{"__id__":6}}],"_prefab":{"__type__":"cc.PrefabInfo","root":{"__id__":1},"asset":{"__uuid__":"f696oT4xtEM7j2K2VK1doP"},"fileId":"49324CUWitKZac3Aaax9B2H"},"_contentSize":{"__type__":"cc.Size","width":191,"height":76},"_position":{"__type__":"cc.Vec3","y":-153},"_scale":{"__type__":"cc.Vec3","x":1,"y":1,"z":1}},{"__type__":"cc.Node","_name":"bd","_parent":{"__id__":6},"_components":[{"__type__":"cc.Sprite","node":{"__id__":7},"_spriteFrame":{"__uuid__":"d2+rzgb2pB1K8ajv2H/ZXz"}}],"_prefab":{"__type__":"cc.PrefabInfo","root":{"__id__":1},"asset":{"__uuid__":"f696oT4xtEM7j2K2VK1doP"},"fileId":"55aaaJ66slOjZy1Ihj4b+yM"},"_contentSize":{"__type__":"cc.Size","width":98,"height":42},"_scale":{"__type__":"cc.Vec3","x":1,"y":1,"z":1}},{"__type__":"cc.Node","_name":"yaoqingma_bg","_parent":{"__id__":1},"_components":[{"__type__":"cc.Sprite","node":{"__id__":8},"_sizeMode":0}],"_prefab":{"__type__":"cc.PrefabInfo","root":{"__id__":1},"asset":{"__uuid__":"f696oT4xtEM7j2K2VK1doP"},"fileId":"465525cZPZHDbh2xu+N9Guc"},"_contentSize":{"__type__":"cc.Size","width":510,"height":90},"_position":{"__type__":"cc.Vec3","x":4,"y":35},"_scale":{"__type__":"cc.Vec3","x":1,"y":1,"z":1}},{"__type__":"cc.Node","_name":"editbox","_parent":{"__id__":1},"_components":[{"__type__":"cc.EditBox","node":{"__id__":9},"_useOriginalSize":false,"_N$inputMode":6,"_N$fontSize":50,"_N$lineHeight":50,"_N$placeholder":"请输入邀请码","_N$placeholderFontSize":50,"_N$placeholderFontColor":{"__type__":"cc.Color","r":243,"g":243,"b":243},"_N$maxLength":6}],"_prefab":{"__type__":"cc.PrefabInfo","root":{"__id__":1},"asset":{"__uuid__":"f696oT4xtEM7j2K2VK1doP"},"fileId":"3374cIhafdPspldeMtKXain"},"_color":{"__type__":"cc.Color","r":255,"g":254,"b":254},"_contentSize":{"__type__":"cc.Size","width":400,"height":70},"_position":{"__type__":"cc.Vec3","x":3,"y":36},"_scale":{"__type__":"cc.Vec3","x":1,"y":1,"z":1}}]]